amde/__init__.py
amde-0.1.6.dist-info/METADATA
amde-0.1.6.dist-info/WHEEL
amde-0.1.6.dist-info/top_level.txt
amde-0.1.6.dist-info/RECORD
