Metadata-Version: 2.4
Name: amde
Version: 0.1.6
Summary: Easy way to embed your data
Author-email: amde <ai.ambade00@gmail.com>
License-Expression: MIT
Requires-Python: >=3.8
Requires-Dist: requests
